badger2040/__init__.py
badger2040/__init__.pyi
badger2040_pystub-0.0.3.dist-info/METADATA
badger2040_pystub-0.0.3.dist-info/WHEEL
badger2040_pystub-0.0.3.dist-info/top_level.txt
badger2040_pystub-0.0.3.dist-info/RECORD
