Metadata-Version: 2.1
Name: badger2040-pystub
Version: 0.0.3
Summary: Python stub file containing documentation and code completion for the Badger2040 hardware
Author-email: V3ntus <joe@gladiusso.com>
Project-URL: Homepage, https://github.com/V3ntus/badger2040-pystub
Project-URL: Bug Tracker, https://github.com/V3ntus/badger2040-pystub/issues
Classifier: Programming Language :: Python :: 3
Classifier: License :: OSI Approved :: MIT License
Classifier: Operating System :: OS Independent
Requires-Python: >=2.7
